bcl2fq/__init__.py
bcl2fq/bcl2fq.py
bcl2fq/qc.py
bcl2fq/bin/bcl2fastq
bcl2fq/bin/fastqc_adapter_pe
bcl2fq/bin/fastqc_adapter_se
bcl2fq_local-0.2.0.dist-info/LICENSE
bcl2fq_local-0.2.0.dist-info/METADATA
bcl2fq_local-0.2.0.dist-info/WHEEL
bcl2fq_local-0.2.0.dist-info/entry_points.txt
bcl2fq_local-0.2.0.dist-info/top_level.txt
bcl2fq_local-0.2.0.dist-info/RECORD
