Metadata-Version: 2.1
Name: bcl2fq-local
Version: 0.2.0
Summary: Bcl2fastq wrapper
Home-page: https://github.com/seahurt/bcl2fq-local
Author: Wang Jianghao
Author-email: haozi.vv@gmail.com
License: MIT
Platform: CentOS 7.0+
Classifier: Development Status :: 4 - Beta
Classifier: Environment :: Console
Classifier: Intended Audience :: Developers
Classifier: Intended Audience :: System Administrators
Classifier: Operating System :: POSIX :: Linux
Classifier: License :: OSI Approved :: MIT License
Classifier: Programming Language :: Python
Classifier: Programming Language :: Python :: 3
Requires-Dist: xmltodict
